{
  "id": "CR-2025-06-09-bug-kr8j",
  "type": "bug",
  "title": "Bug Fix: Critical priority identification is spot-on.: The ...",
  "description": "## CodeRabbit Suggestion\n\n**Category:** bug\n**Priority:** high\n**Source PR:** #undefined\n\n### Suggestion Details\nCritical priority identification is spot-on.: The p5.js instance mode violations are correctly identified as the highest priority. This will prevent runtime crashes and namespace pollution. The fix pattern provided is clear and actionable.\n\n### Implementation Notes\n- Review the original CodeRabbit suggestion in PR #undefined\n- Implement the suggested changes following project coding standards\n- Test thoroughly before creating a pull request\n- Update this ticket status when work begins and completes\n\n### Acceptance Criteria\n- [ ] Review original CodeRabbit suggestion\n- [ ] Implement suggested changes\n- [ ] Add appropriate tests\n- [ ] Update documentation if needed\n- [ ] Create pull request with changes\n- [ ] Verify CodeRabbit approval in new PR\n\n### Tracking\n- **Suggestion Hash:** dW5kZWZpbmVkLWJ1Zy1Dcml0aWNhbCBw\n- **Generated:** 2025-06-09T00:41:17.307Z\n\n---\n*This ticket was automatically generated from CodeRabbit review suggestions.*",
  "tags": [
    "coderabbit",
    "bug",
    "auto-generated"
  ],
  "status": "open",
  "priority": "high",
  "source": "coderabbit",
  "pullRequest": "#undefined",
  "coderabbitSuggestion": "Critical priority identification is spot-on.: The p5.js instance mode violations are correctly identified as the highest priority. This will prevent runtime crashes and namespace pollution. The fix pattern provided is clear and actionable.",
  "suggestionHash": "dW5kZWZpbmVkLWJ1Zy1Dcml0aWNhbCBw",
  "file": null,
  "line": null,
  "reviewUrl": null,
  "artifacts": [],
  "relatedTickets": [],
  "createdAt": "2025-06-09T00:41:17.307Z",
  "updatedAt": "2025-06-09T00:41:17.307Z",
  "timestamp": "2025-06-09T00:41:17.307Z",
  "history": [],
  "verification": []
}