{
  "id": "CR-2025-06-09-bug-zdqp",
  "type": "bug",
  "title": "Bug Fix: Verify uncommenting of BaseEnemy.js and bullet.js....",
  "description": "## CodeRabbit Suggestion\n\n**Category:** bug\n**Priority:** high\n**Source PR:** #undefined\n\n### Suggestion Details\nVerify uncommenting of BaseEnemy.js and bullet.js.: These scripts were previously commented out and are now enabled. Ensure this doesn't introduce any runtime errors or conflicts with existing functionality.\n\n### Implementation Notes\n- Review the original CodeRabbit suggestion in PR #undefined\n- Implement the suggested changes following project coding standards\n- Test thoroughly before creating a pull request\n- Update this ticket status when work begins and completes\n\n### Acceptance Criteria\n- [ ] Review original CodeRabbit suggestion\n- [ ] Implement suggested changes\n- [ ] Add appropriate tests\n- [ ] Update documentation if needed\n- [ ] Create pull request with changes\n- [ ] Verify CodeRabbit approval in new PR\n\n### Tracking\n- **Suggestion Hash:** dW5kZWZpbmVkLWJ1Zy1WZXJpZnkgdW5j\n- **Generated:** 2025-06-09T00:41:21.453Z\n\n---\n*This ticket was automatically generated from CodeRabbit review suggestions.*",
  "tags": [
    "coderabbit",
    "bug",
    "auto-generated"
  ],
  "status": "open",
  "priority": "high",
  "source": "coderabbit",
  "pullRequest": "#undefined",
  "coderabbitSuggestion": "Verify uncommenting of BaseEnemy.js and bullet.js.: These scripts were previously commented out and are now enabled. Ensure this doesn't introduce any runtime errors or conflicts with existing functionality.",
  "suggestionHash": "dW5kZWZpbmVkLWJ1Zy1WZXJpZnkgdW5j",
  "file": null,
  "line": null,
  "reviewUrl": null,
  "artifacts": [],
  "relatedTickets": [],
  "createdAt": "2025-06-09T00:41:21.453Z",
  "updatedAt": "2025-06-09T00:41:21.453Z",
  "timestamp": "2025-06-09T00:41:21.453Z",
  "history": [],
  "verification": []
}