{
  "id": "CR-2025-06-09-bug-s03w",
  "type": "bug",
  "title": "Bug Fix: [error] 299-299: Replace `············report.recom...",
  "description": "## CodeRabbit Suggestion\n\n**Category:** bug\n**Priority:** high\n**Source PR:** #undefined\n\n### Suggestion Details\n[error] 299-299: Replace `············report.recommendations.push(`🎯·${results.created}·new·tickets·created·-·review·and·prioritize·them`);` with `······report.recommendations.push(⏎········`🎯·${results.created}·new·tickets·created·-·review·and·prioritize·them``\n\n### Implementation Notes\n- Review the original CodeRabbit suggestion in PR #undefined\n- Implement the suggested changes following project coding standards\n- Test thoroughly before creating a pull request\n- Update this ticket status when work begins and completes\n\n### Acceptance Criteria\n- [ ] Review original CodeRabbit suggestion\n- [ ] Implement suggested changes\n- [ ] Add appropriate tests\n- [ ] Update documentation if needed\n- [ ] Create pull request with changes\n- [ ] Verify CodeRabbit approval in new PR\n\n### Tracking\n- **Suggestion Hash:** dW5kZWZpbmVkLWJ1Zy1bZXJyb3JdIDI5\n- **Generated:** 2025-06-09T00:41:22.025Z\n\n---\n*This ticket was automatically generated from CodeRabbit review suggestions.*",
  "tags": [
    "coderabbit",
    "bug",
    "auto-generated"
  ],
  "status": "open",
  "priority": "high",
  "source": "coderabbit",
  "pullRequest": "#undefined",
  "coderabbitSuggestion": "[error] 299-299: Replace `············report.recommendations.push(`🎯·${results.created}·new·tickets·created·-·review·and·prioritize·them`);` with `······report.recommendations.push(⏎········`🎯·${results.created}·new·tickets·created·-·review·and·prioritize·them``",
  "suggestionHash": "dW5kZWZpbmVkLWJ1Zy1bZXJyb3JdIDI5",
  "file": null,
  "line": null,
  "reviewUrl": null,
  "artifacts": [],
  "relatedTickets": [],
  "createdAt": "2025-06-09T00:41:22.025Z",
  "updatedAt": "2025-06-09T00:41:22.025Z",
  "timestamp": "2025-06-09T00:41:22.025Z",
  "history": [],
  "verification": []
}