{
  "id": "CR-2025-06-09-bug-auiu",
  "type": "bug",
  "title": "Bug Fix: LGTM! Consistent addition of \"task\" ticket type.: ...",
  "description": "## CodeRabbit Suggestion\n\n**Category:** bug\n**Priority:** high\n**Source PR:** #undefined\n\n### Suggestion Details\nLGTM! Consistent addition of \"task\" ticket type.: The changes properly extend validation to support the new \"task\" ticket type by updating both the error message and the allowedTypes array. Implementation is consistent with existing patterns.\n\n### Implementation Notes\n- Review the original CodeRabbit suggestion in PR #undefined\n- Implement the suggested changes following project coding standards\n- Test thoroughly before creating a pull request\n- Update this ticket status when work begins and completes\n\n### Acceptance Criteria\n- [ ] Review original CodeRabbit suggestion\n- [ ] Implement suggested changes\n- [ ] Add appropriate tests\n- [ ] Update documentation if needed\n- [ ] Create pull request with changes\n- [ ] Verify CodeRabbit approval in new PR\n\n### Tracking\n- **Suggestion Hash:** dW5kZWZpbmVkLWJ1Zy1MR1RNISBDb25z\n- **Generated:** 2025-06-09T00:41:20.729Z\n\n---\n*This ticket was automatically generated from CodeRabbit review suggestions.*",
  "tags": [
    "coderabbit",
    "bug",
    "auto-generated"
  ],
  "status": "open",
  "priority": "high",
  "source": "coderabbit",
  "pullRequest": "#undefined",
  "coderabbitSuggestion": "LGTM! Consistent addition of \"task\" ticket type.: The changes properly extend validation to support the new \"task\" ticket type by updating both the error message and the allowedTypes array. Implementation is consistent with existing patterns.",
  "suggestionHash": "dW5kZWZpbmVkLWJ1Zy1MR1RNISBDb25z",
  "file": null,
  "line": null,
  "reviewUrl": null,
  "artifacts": [],
  "relatedTickets": [],
  "createdAt": "2025-06-09T00:41:20.729Z",
  "updatedAt": "2025-06-09T00:41:20.729Z",
  "timestamp": "2025-06-09T00:41:20.729Z",
  "history": [],
  "verification": []
}