{
  "id": "CR-2025-06-09-bug-5jyr",
  "type": "bug",
  "title": "Bug Fix: Consider documenting the root causes of test failu...",
  "description": "## CodeRabbit Suggestion\n\n**Category:** bug\n**Priority:** high\n**Source PR:** #undefined\n\n### Suggestion Details\nConsider documenting the root causes of test failures.: The report lists several test failures (AI Liveness Probe, Shooting Mechanics Tests, etc.) but doesn't provide root cause analysis. Understanding why these tests fail would be valuable for prioritizing fixes.\n\n### Implementation Notes\n- Review the original CodeRabbit suggestion in PR #undefined\n- Implement the suggested changes following project coding standards\n- Test thoroughly before creating a pull request\n- Update this ticket status when work begins and completes\n\n### Acceptance Criteria\n- [ ] Review original CodeRabbit suggestion\n- [ ] Implement suggested changes\n- [ ] Add appropriate tests\n- [ ] Update documentation if needed\n- [ ] Create pull request with changes\n- [ ] Verify CodeRabbit approval in new PR\n\n### Tracking\n- **Suggestion Hash:** dW5kZWZpbmVkLWJ1Zy1Db25zaWRlciBk\n- **Generated:** 2025-06-09T00:41:21.431Z\n\n---\n*This ticket was automatically generated from CodeRabbit review suggestions.*",
  "tags": [
    "coderabbit",
    "bug",
    "auto-generated"
  ],
  "status": "open",
  "priority": "high",
  "source": "coderabbit",
  "pullRequest": "#undefined",
  "coderabbitSuggestion": "Consider documenting the root causes of test failures.: The report lists several test failures (AI Liveness Probe, Shooting Mechanics Tests, etc.) but doesn't provide root cause analysis. Understanding why these tests fail would be valuable for prioritizing fixes.",
  "suggestionHash": "dW5kZWZpbmVkLWJ1Zy1Db25zaWRlciBk",
  "file": null,
  "line": null,
  "reviewUrl": null,
  "artifacts": [],
  "relatedTickets": [],
  "createdAt": "2025-06-09T00:41:21.431Z",
  "updatedAt": "2025-06-09T00:41:21.431Z",
  "timestamp": "2025-06-09T00:41:21.431Z",
  "history": [],
  "verification": []
}