{
  "id": "CR-2025-06-09-bug-bmp3",
  "type": "bug",
  "title": "Bug Fix: Well-structured audio system probe following estab...",
  "description": "## CodeRabbit Suggestion\n\n**Category:** bug\n**Priority:** high\n**Source PR:** #undefined\n\n### Suggestion Details\nWell-structured audio system probe following established patterns.: The probe module follows the consistent pattern established by other probe files (ui-score-probe.js, enemy-ai-probe.js, combat-collision-probe.js) with proper error handling, warning collection, and automated bug reporting.\n\n### Implementation Notes\n- Review the original CodeRabbit suggestion in PR #undefined\n- Implement the suggested changes following project coding standards\n- Test thoroughly before creating a pull request\n- Update this ticket status when work begins and completes\n\n### Acceptance Criteria\n- [ ] Review original CodeRabbit suggestion\n- [ ] Implement suggested changes\n- [ ] Add appropriate tests\n- [ ] Update documentation if needed\n- [ ] Create pull request with changes\n- [ ] Verify CodeRabbit approval in new PR\n\n### Tracking\n- **Suggestion Hash:** dW5kZWZpbmVkLWJ1Zy1XZWxsLXN0cnVj\n- **Generated:** 2025-06-09T00:41:17.732Z\n\n---\n*This ticket was automatically generated from CodeRabbit review suggestions.*",
  "tags": [
    "coderabbit",
    "bug",
    "auto-generated"
  ],
  "status": "open",
  "priority": "high",
  "source": "coderabbit",
  "pullRequest": "#undefined",
  "coderabbitSuggestion": "Well-structured audio system probe following established patterns.: The probe module follows the consistent pattern established by other probe files (ui-score-probe.js, enemy-ai-probe.js, combat-collision-probe.js) with proper error handling, warning collection, and automated bug reporting.",
  "suggestionHash": "dW5kZWZpbmVkLWJ1Zy1XZWxsLXN0cnVj",
  "file": null,
  "line": null,
  "reviewUrl": null,
  "artifacts": [],
  "relatedTickets": [],
  "createdAt": "2025-06-09T00:41:17.732Z",
  "updatedAt": "2025-06-09T00:41:17.732Z",
  "timestamp": "2025-06-09T00:41:17.732Z",
  "history": [],
  "verification": []
}