{
  "id": "CR-2025-06-09-sec-eewx",
  "type": "enhancement",
  "title": "Security Improvement: Excellent security improvement using environment v...",
  "description": "## CodeRabbit Suggestion\n\n**Category:** security\n**Priority:** high\n**Source PR:** #undefined\n\n### Suggestion Details\nExcellent security improvement using environment variables.: Moving the API key from hardcoded values to environment variables is a significant security enhancement. The implementation correctly:\n\n### Implementation Notes\n- Review the original CodeRabbit suggestion in PR #undefined\n- Implement the suggested changes following project coding standards\n- Test thoroughly before creating a pull request\n- Update this ticket status when work begins and completes\n\n### Acceptance Criteria\n- [ ] Review original CodeRabbit suggestion\n- [ ] Implement suggested changes\n- [ ] Add appropriate tests\n- [ ] Update documentation if needed\n- [ ] Create pull request with changes\n- [ ] Verify CodeRabbit approval in new PR\n\n### Tracking\n- **Suggestion Hash:** dW5kZWZpbmVkLXNlY3VyaXR5LUV4Y2Vs\n- **Generated:** 2025-06-09T00:41:13.179Z\n\n---\n*This ticket was automatically generated from CodeRabbit review suggestions.*",
  "tags": [
    "coderabbit",
    "security",
    "auto-generated"
  ],
  "status": "open",
  "priority": "high",
  "source": "coderabbit",
  "pullRequest": "#undefined",
  "coderabbitSuggestion": "Excellent security improvement using environment variables.: Moving the API key from hardcoded values to environment variables is a significant security enhancement. The implementation correctly:",
  "suggestionHash": "dW5kZWZpbmVkLXNlY3VyaXR5LUV4Y2Vs",
  "file": null,
  "line": null,
  "reviewUrl": null,
  "artifacts": [],
  "relatedTickets": [],
  "createdAt": "2025-06-09T00:41:13.179Z",
  "updatedAt": "2025-06-09T00:41:13.179Z",
  "timestamp": "2025-06-09T00:41:13.179Z",
  "history": [],
  "verification": []
}