{
  "id": "CR-2025-06-09-bug-ybti",
  "type": "bug",
  "title": "Bug Fix: Valuable best practices section!: The testing phil...",
  "description": "## CodeRabbit Suggestion\n\n**Category:** bug\n**Priority:** high\n**Source PR:** #undefined\n\n### Suggestion Details\nValuable best practices section!: The testing philosophy, code quality guidelines, and team collaboration practices provide excellent guidance beyond just the mechanics of testing. The emphasis on \"Test reality first\" and \"Fail fast\" aligns well with modern testing practices.\n\n### Implementation Notes\n- Review the original CodeRabbit suggestion in PR #undefined\n- Implement the suggested changes following project coding standards\n- Test thoroughly before creating a pull request\n- Update this ticket status when work begins and completes\n\n### Acceptance Criteria\n- [ ] Review original CodeRabbit suggestion\n- [ ] Implement suggested changes\n- [ ] Add appropriate tests\n- [ ] Update documentation if needed\n- [ ] Create pull request with changes\n- [ ] Verify CodeRabbit approval in new PR\n\n### Tracking\n- **Suggestion Hash:** dW5kZWZpbmVkLWJ1Zy1WYWx1YWJsZSBi\n- **Generated:** 2025-06-09T00:41:22.367Z\n\n---\n*This ticket was automatically generated from CodeRabbit review suggestions.*",
  "tags": [
    "coderabbit",
    "bug",
    "auto-generated"
  ],
  "status": "open",
  "priority": "high",
  "source": "coderabbit",
  "pullRequest": "#undefined",
  "coderabbitSuggestion": "Valuable best practices section!: The testing philosophy, code quality guidelines, and team collaboration practices provide excellent guidance beyond just the mechanics of testing. The emphasis on \"Test reality first\" and \"Fail fast\" aligns well with modern testing practices.",
  "suggestionHash": "dW5kZWZpbmVkLWJ1Zy1WYWx1YWJsZSBi",
  "file": null,
  "line": null,
  "reviewUrl": null,
  "artifacts": [],
  "relatedTickets": [],
  "createdAt": "2025-06-09T00:41:22.367Z",
  "updatedAt": "2025-06-09T00:41:22.367Z",
  "timestamp": "2025-06-09T00:41:22.367Z",
  "history": [],
  "verification": []
}