{
  "id": "CR-2025-06-09-bug-w6ux",
  "type": "bug",
  "title": "Bug Fix: Realistic and well-structured timeline.: The 4-wee...",
  "description": "## CodeRabbit Suggestion\n\n**Category:** bug\n**Priority:** high\n**Source PR:** #undefined\n\n### Suggestion Details\nRealistic and well-structured timeline.: The 4-week fix schedule is practical and properly sequences the work from critical bugs to code standards. This approach minimizes risk of introducing new issues.\n\n### Implementation Notes\n- Review the original CodeRabbit suggestion in PR #undefined\n- Implement the suggested changes following project coding standards\n- Test thoroughly before creating a pull request\n- Update this ticket status when work begins and completes\n\n### Acceptance Criteria\n- [ ] Review original CodeRabbit suggestion\n- [ ] Implement suggested changes\n- [ ] Add appropriate tests\n- [ ] Update documentation if needed\n- [ ] Create pull request with changes\n- [ ] Verify CodeRabbit approval in new PR\n\n### Tracking\n- **Suggestion Hash:** dW5kZWZpbmVkLWJ1Zy1SZWFsaXN0aWMg\n- **Generated:** 2025-06-09T00:41:17.457Z\n\n---\n*This ticket was automatically generated from CodeRabbit review suggestions.*",
  "tags": [
    "coderabbit",
    "bug",
    "auto-generated"
  ],
  "status": "open",
  "priority": "high",
  "source": "coderabbit",
  "pullRequest": "#undefined",
  "coderabbitSuggestion": "Realistic and well-structured timeline.: The 4-week fix schedule is practical and properly sequences the work from critical bugs to code standards. This approach minimizes risk of introducing new issues.",
  "suggestionHash": "dW5kZWZpbmVkLWJ1Zy1SZWFsaXN0aWMg",
  "file": null,
  "line": null,
  "reviewUrl": null,
  "artifacts": [],
  "relatedTickets": [],
  "createdAt": "2025-06-09T00:41:17.457Z",
  "updatedAt": "2025-06-09T00:41:17.457Z",
  "timestamp": "2025-06-09T00:41:17.457Z",
  "history": [],
  "verification": []
}