{
  "id": "CR-2025-06-09-bug-xvj7",
  "type": "bug",
  "title": "Bug Fix: [error] 202-202: Replace `········const·category·=...",
  "description": "## CodeRabbit Suggestion\n\n**Category:** bug\n**Priority:** high\n**Source PR:** #undefined\n\n### Suggestion Details\n[error] 202-202: Replace `········const·category·=·suggestion.category.charAt(0).toUpperCase()·+` with `····const·category·=⏎······suggestion.category.charAt(0).toUpperCase()·+⏎·····`\n\n### Implementation Notes\n- Review the original CodeRabbit suggestion in PR #undefined\n- Implement the suggested changes following project coding standards\n- Test thoroughly before creating a pull request\n- Update this ticket status when work begins and completes\n\n### Acceptance Criteria\n- [ ] Review original CodeRabbit suggestion\n- [ ] Implement suggested changes\n- [ ] Add appropriate tests\n- [ ] Update documentation if needed\n- [ ] Create pull request with changes\n- [ ] Verify CodeRabbit approval in new PR\n\n### Tracking\n- **Suggestion Hash:** dW5kZWZpbmVkLWJ1Zy1bZXJyb3JdIDIw\n- **Generated:** 2025-06-09T00:41:13.263Z\n\n---\n*This ticket was automatically generated from CodeRabbit review suggestions.*",
  "tags": [
    "coderabbit",
    "bug",
    "auto-generated"
  ],
  "status": "open",
  "priority": "high",
  "source": "coderabbit",
  "pullRequest": "#undefined",
  "coderabbitSuggestion": "[error] 202-202: Replace `········const·category·=·suggestion.category.charAt(0).toUpperCase()·+` with `····const·category·=⏎······suggestion.category.charAt(0).toUpperCase()·+⏎·····`",
  "suggestionHash": "dW5kZWZpbmVkLWJ1Zy1bZXJyb3JdIDIw",
  "file": null,
  "line": null,
  "reviewUrl": null,
  "artifacts": [],
  "relatedTickets": [],
  "createdAt": "2025-06-09T00:41:13.263Z",
  "updatedAt": "2025-06-09T00:41:13.263Z",
  "timestamp": "2025-06-09T00:41:13.263Z",
  "history": [],
  "verification": []
}