{
  "id": "CR-2025-06-09-bug-omrp",
  "type": "bug",
  "title": "Bug Fix: Review statistical claims for accuracy.: The execu...",
  "description": "## CodeRabbit Suggestion\n\n**Category:** bug\n**Priority:** high\n**Source PR:** #undefined\n\n### Suggestion Details\nReview statistical claims for accuracy.: The executive summary claims very specific numbers (54 total issues, 25 critical bugs, etc.) that should be validated. Consider whether these numbers accurately reflect the current state of the codebase or if they're based on outdated analysis.\n\n### Implementation Notes\n- Review the original CodeRabbit suggestion in PR #undefined\n- Implement the suggested changes following project coding standards\n- Test thoroughly before creating a pull request\n- Update this ticket status when work begins and completes\n\n### Acceptance Criteria\n- [ ] Review original CodeRabbit suggestion\n- [ ] Implement suggested changes\n- [ ] Add appropriate tests\n- [ ] Update documentation if needed\n- [ ] Create pull request with changes\n- [ ] Verify CodeRabbit approval in new PR\n\n### Tracking\n- **Suggestion Hash:** dW5kZWZpbmVkLWJ1Zy1SZXZpZXcgc3Rh\n- **Generated:** 2025-06-09T00:41:17.031Z\n\n---\n*This ticket was automatically generated from CodeRabbit review suggestions.*",
  "tags": [
    "coderabbit",
    "bug",
    "auto-generated"
  ],
  "status": "open",
  "priority": "high",
  "source": "coderabbit",
  "pullRequest": "#undefined",
  "coderabbitSuggestion": "Review statistical claims for accuracy.: The executive summary claims very specific numbers (54 total issues, 25 critical bugs, etc.) that should be validated. Consider whether these numbers accurately reflect the current state of the codebase or if they're based on outdated analysis.",
  "suggestionHash": "dW5kZWZpbmVkLWJ1Zy1SZXZpZXcgc3Rh",
  "file": null,
  "line": null,
  "reviewUrl": null,
  "artifacts": [],
  "relatedTickets": [],
  "createdAt": "2025-06-09T00:41:17.031Z",
  "updatedAt": "2025-06-09T00:41:17.031Z",
  "timestamp": "2025-06-09T00:41:17.031Z",
  "history": [],
  "verification": []
}