{
  "id": "CR-2025-06-09-bug-dr6c",
  "type": "bug",
  "title": "Bug Fix: Consider splitting into multiple focused documents...",
  "description": "## CodeRabbit Suggestion\n\n**Category:** bug\n**Priority:** high\n**Source PR:** #undefined\n\n### Suggestion Details\nConsider splitting into multiple focused documents\n\n\n\nApply these fixes for better markdown formatting:\n\n```diff\n-```\n+```text\n📊 Test Results:\n  ✅ PASS Server Status\n  ✅ PASS Game Files  \n  ❌ FAIL JavaScript Syntax (emoji compliance only)\n  ✅ PASS Consistency Rules\n\n📈 Success Rate: 75.\n\n### Implementation Notes\n- Review the original CodeRabbit suggestion in PR #undefined\n- Implement the suggested changes following project coding standards\n- Test thoroughly before creating a pull request\n- Update this ticket status when work begins and completes\n\n### Acceptance Criteria\n- [ ] Review original CodeRabbit suggestion\n- [ ] Implement suggested changes\n- [ ] Add appropriate tests\n- [ ] Update documentation if needed\n- [ ] Create pull request with changes\n- [ ] Verify CodeRabbit approval in new PR\n\n### Tracking\n- **Suggestion Hash:** dW5kZWZpbmVkLWJ1Zy1Db25zaWRlciBz\n- **Generated:** 2025-06-09T00:41:17.846Z\n\n---\n*This ticket was automatically generated from CodeRabbit review suggestions.*",
  "tags": [
    "coderabbit",
    "bug",
    "auto-generated"
  ],
  "status": "open",
  "priority": "high",
  "source": "coderabbit",
  "pullRequest": "#undefined",
  "coderabbitSuggestion": "Consider splitting into multiple focused documents\n\n\n\nApply these fixes for better markdown formatting:\n\n```diff\n-```\n+```text\n📊 Test Results:\n  ✅ PASS Server Status\n  ✅ PASS Game Files  \n  ❌ FAIL JavaScript Syntax (emoji compliance only)\n  ✅ PASS Consistency Rules\n\n📈 Success Rate: 75.",
  "suggestionHash": "dW5kZWZpbmVkLWJ1Zy1Db25zaWRlciBz",
  "file": null,
  "line": null,
  "reviewUrl": null,
  "artifacts": [],
  "relatedTickets": [],
  "createdAt": "2025-06-09T00:41:17.846Z",
  "updatedAt": "2025-06-09T00:41:17.846Z",
  "timestamp": "2025-06-09T00:41:17.846Z",
  "history": [],
  "verification": []
}