{
  "id": "CR-2025-06-09-bug-y2oq",
  "type": "bug",
  "title": "Bug Fix: Add null check for window.player: The code checks ...",
  "description": "## CodeRabbit Suggestion\n\n**Category:** bug\n**Priority:** high\n**Source PR:** #undefined\n\n### Suggestion Details\nAdd null check for window.player: The code checks for window.player existence but continues to use it afterward without rechecking, which could lead to null reference errors if the player object is removed during execution.\n\n### Implementation Notes\n- Review the original CodeRabbit suggestion in PR #undefined\n- Implement the suggested changes following project coding standards\n- Test thoroughly before creating a pull request\n- Update this ticket status when work begins and completes\n\n### Acceptance Criteria\n- [ ] Review original CodeRabbit suggestion\n- [ ] Implement suggested changes\n- [ ] Add appropriate tests\n- [ ] Update documentation if needed\n- [ ] Create pull request with changes\n- [ ] Verify CodeRabbit approval in new PR\n\n### Tracking\n- **Suggestion Hash:** dW5kZWZpbmVkLWJ1Zy1BZGQgbnVsbCBj\n- **Generated:** 2025-06-09T00:41:22.555Z\n\n---\n*This ticket was automatically generated from CodeRabbit review suggestions.*",
  "tags": [
    "coderabbit",
    "bug",
    "auto-generated"
  ],
  "status": "open",
  "priority": "high",
  "source": "coderabbit",
  "pullRequest": "#undefined",
  "coderabbitSuggestion": "Add null check for window.player: The code checks for window.player existence but continues to use it afterward without rechecking, which could lead to null reference errors if the player object is removed during execution.",
  "suggestionHash": "dW5kZWZpbmVkLWJ1Zy1BZGQgbnVsbCBj",
  "file": null,
  "line": null,
  "reviewUrl": null,
  "artifacts": [],
  "relatedTickets": [],
  "createdAt": "2025-06-09T00:41:22.555Z",
  "updatedAt": "2025-06-09T00:41:22.555Z",
  "timestamp": "2025-06-09T00:41:22.555Z",
  "history": [],
  "verification": []
}