{
  "id": "CR-2025-06-09-bug-wz9b",
  "type": "bug",
  "title": "Bug Fix: Resolve probe path & validate existence to avoid s...",
  "description": "## CodeRabbit Suggestion\n\n**Category:** bug\n**Priority:** high\n**Source PR:** #undefined\n\n### Suggestion Details\nResolve probe path & validate existence to avoid silent `ENOENT`: Reading a relative path from an arbitrary CWD is brittle. Resolve against project root and fail fast with a clear error.\n\n### Implementation Notes\n- Review the original CodeRabbit suggestion in PR #undefined\n- Implement the suggested changes following project coding standards\n- Test thoroughly before creating a pull request\n- Update this ticket status when work begins and completes\n\n### Acceptance Criteria\n- [ ] Review original CodeRabbit suggestion\n- [ ] Implement suggested changes\n- [ ] Add appropriate tests\n- [ ] Update documentation if needed\n- [ ] Create pull request with changes\n- [ ] Verify CodeRabbit approval in new PR\n\n### Tracking\n- **Suggestion Hash:** dW5kZWZpbmVkLWJ1Zy1SZXNvbHZlIHBy\n- **Generated:** 2025-06-09T00:41:22.677Z\n\n---\n*This ticket was automatically generated from CodeRabbit review suggestions.*",
  "tags": [
    "coderabbit",
    "bug",
    "auto-generated"
  ],
  "status": "open",
  "priority": "high",
  "source": "coderabbit",
  "pullRequest": "#undefined",
  "coderabbitSuggestion": "Resolve probe path & validate existence to avoid silent `ENOENT`: Reading a relative path from an arbitrary CWD is brittle. Resolve against project root and fail fast with a clear error.",
  "suggestionHash": "dW5kZWZpbmVkLWJ1Zy1SZXNvbHZlIHBy",
  "file": null,
  "line": null,
  "reviewUrl": null,
  "artifacts": [],
  "relatedTickets": [],
  "createdAt": "2025-06-09T00:41:22.677Z",
  "updatedAt": "2025-06-09T00:41:22.677Z",
  "timestamp": "2025-06-09T00:41:22.677Z",
  "history": [],
  "verification": []
}