{
  "id": "CR-2025-06-09-bug-6mz1",
  "type": "bug",
  "title": "Bug Fix: `npm run test:automated` is re-executed inside the...",
  "description": "## CodeRabbit Suggestion\n\n**Category:** bug\n**Priority:** high\n**Source PR:** #undefined\n\n### Suggestion Details\n`npm run test:automated` is re-executed inside the markdown step: This can double test duration and may fail because previous steps left the repo in a different state. Persist the earlier exit code instead of rerunning:\n\n### Implementation Notes\n- Review the original CodeRabbit suggestion in PR #undefined\n- Implement the suggested changes following project coding standards\n- Test thoroughly before creating a pull request\n- Update this ticket status when work begins and completes\n\n### Acceptance Criteria\n- [ ] Review original CodeRabbit suggestion\n- [ ] Implement suggested changes\n- [ ] Add appropriate tests\n- [ ] Update documentation if needed\n- [ ] Create pull request with changes\n- [ ] Verify CodeRabbit approval in new PR\n\n### Tracking\n- **Suggestion Hash:** dW5kZWZpbmVkLWJ1Zy1gbnBtIHJ1biB0\n- **Generated:** 2025-06-09T00:41:19.866Z\n\n---\n*This ticket was automatically generated from CodeRabbit review suggestions.*",
  "tags": [
    "coderabbit",
    "bug",
    "auto-generated"
  ],
  "status": "open",
  "priority": "high",
  "source": "coderabbit",
  "pullRequest": "#undefined",
  "coderabbitSuggestion": "`npm run test:automated` is re-executed inside the markdown step: This can double test duration and may fail because previous steps left the repo in a different state. Persist the earlier exit code instead of rerunning:",
  "suggestionHash": "dW5kZWZpbmVkLWJ1Zy1gbnBtIHJ1biB0",
  "file": null,
  "line": null,
  "reviewUrl": null,
  "artifacts": [],
  "relatedTickets": [],
  "createdAt": "2025-06-09T00:41:19.866Z",
  "updatedAt": "2025-06-09T00:41:19.866Z",
  "timestamp": "2025-06-09T00:41:19.866Z",
  "history": [],
  "verification": []
}