{
  "id": "CR-2025-06-09-bug-nhod",
  "type": "bug",
  "title": "Bug Fix: The `getJavaScriptErrors` method has some defensiv...",
  "description": "## CodeRabbit Suggestion\n\n**Category:** bug\n**Priority:** high\n**Source PR:** #undefined\n\n### Suggestion Details\nThe `getJavaScriptErrors` method has some defensive programming but could be more robust in handling undefined objects.\n\n### Implementation Notes\n- Review the original CodeRabbit suggestion in PR #undefined\n- Implement the suggested changes following project coding standards\n- Test thoroughly before creating a pull request\n- Update this ticket status when work begins and completes\n\n### Acceptance Criteria\n- [ ] Review original CodeRabbit suggestion\n- [ ] Implement suggested changes\n- [ ] Add appropriate tests\n- [ ] Update documentation if needed\n- [ ] Create pull request with changes\n- [ ] Verify CodeRabbit approval in new PR\n\n### Tracking\n- **Suggestion Hash:** dW5kZWZpbmVkLWJ1Zy1UaGUgYGdldEph\n- **Generated:** 2025-06-09T00:41:22.614Z\n\n---\n*This ticket was automatically generated from CodeRabbit review suggestions.*",
  "tags": [
    "coderabbit",
    "bug",
    "auto-generated"
  ],
  "status": "open",
  "priority": "high",
  "source": "coderabbit",
  "pullRequest": "#undefined",
  "coderabbitSuggestion": "The `getJavaScriptErrors` method has some defensive programming but could be more robust in handling undefined objects.",
  "suggestionHash": "dW5kZWZpbmVkLWJ1Zy1UaGUgYGdldEph",
  "file": null,
  "line": null,
  "reviewUrl": null,
  "artifacts": [],
  "relatedTickets": [],
  "createdAt": "2025-06-09T00:41:22.614Z",
  "updatedAt": "2025-06-09T00:41:22.614Z",
  "timestamp": "2025-06-09T00:41:22.614Z",
  "history": [],
  "verification": []
}