{
  "id": "CR-2025-06-09-bug-sazp",
  "type": "bug",
  "title": "Bug Fix: Ad-hoc “syntax” checker produces many false positi...",
  "description": "## CodeRabbit Suggestion\n\n**Category:** bug\n**Priority:** high\n**Source PR:** #undefined\n\n### Suggestion Details\nAd-hoc “syntax” checker produces many false positives: The current line-by-line brace counter and “import without export” heuristics will incorrectly fail on perfectly valid modules (e.g., side-effect-only imports, template literals, multiline objects). They also miss real errors such as unmatched braces spanning multiple lines.\n\n### Implementation Notes\n- Review the original CodeRabbit suggestion in PR #undefined\n- Implement the suggested changes following project coding standards\n- Test thoroughly before creating a pull request\n- Update this ticket status when work begins and completes\n\n### Acceptance Criteria\n- [ ] Review original CodeRabbit suggestion\n- [ ] Implement suggested changes\n- [ ] Add appropriate tests\n- [ ] Update documentation if needed\n- [ ] Create pull request with changes\n- [ ] Verify CodeRabbit approval in new PR\n\n### Tracking\n- **Suggestion Hash:** dW5kZWZpbmVkLWJ1Zy1BZC1ob2Mg4oCc\n- **Generated:** 2025-06-09T00:41:16.674Z\n\n---\n*This ticket was automatically generated from CodeRabbit review suggestions.*",
  "tags": [
    "coderabbit",
    "bug",
    "auto-generated"
  ],
  "status": "open",
  "priority": "high",
  "source": "coderabbit",
  "pullRequest": "#undefined",
  "coderabbitSuggestion": "Ad-hoc “syntax” checker produces many false positives: The current line-by-line brace counter and “import without export” heuristics will incorrectly fail on perfectly valid modules (e.g., side-effect-only imports, template literals, multiline objects). They also miss real errors such as unmatched braces spanning multiple lines.",
  "suggestionHash": "dW5kZWZpbmVkLWJ1Zy1BZC1ob2Mg4oCc",
  "file": null,
  "line": null,
  "reviewUrl": null,
  "artifacts": [],
  "relatedTickets": [],
  "createdAt": "2025-06-09T00:41:16.674Z",
  "updatedAt": "2025-06-09T00:41:16.674Z",
  "timestamp": "2025-06-09T00:41:16.674Z",
  "history": [],
  "verification": []
}