{
  "id": "CR-2025-06-09-bug-s338",
  "type": "bug",
  "title": "Bug Fix: Good defensive programming - consider adding error...",
  "description": "## CodeRabbit Suggestion\n\n**Category:** bug\n**Priority:** high\n**Source PR:** #undefined\n\n### Suggestion Details\nGood defensive programming - consider adding error handling.: The directory existence check and creation logic is a solid improvement that prevents potential file write failures. The synchronous approach is appropriate for this setup phase.\n\n### Implementation Notes\n- Review the original CodeRabbit suggestion in PR #undefined\n- Implement the suggested changes following project coding standards\n- Test thoroughly before creating a pull request\n- Update this ticket status when work begins and completes\n\n### Acceptance Criteria\n- [ ] Review original CodeRabbit suggestion\n- [ ] Implement suggested changes\n- [ ] Add appropriate tests\n- [ ] Update documentation if needed\n- [ ] Create pull request with changes\n- [ ] Verify CodeRabbit approval in new PR\n\n### Tracking\n- **Suggestion Hash:** dW5kZWZpbmVkLWJ1Zy1Hb29kIGRlZmVu\n- **Generated:** 2025-06-09T00:41:15.663Z\n\n---\n*This ticket was automatically generated from CodeRabbit review suggestions.*",
  "tags": [
    "coderabbit",
    "bug",
    "auto-generated"
  ],
  "status": "open",
  "priority": "high",
  "source": "coderabbit",
  "pullRequest": "#undefined",
  "coderabbitSuggestion": "Good defensive programming - consider adding error handling.: The directory existence check and creation logic is a solid improvement that prevents potential file write failures. The synchronous approach is appropriate for this setup phase.",
  "suggestionHash": "dW5kZWZpbmVkLWJ1Zy1Hb29kIGRlZmVu",
  "file": null,
  "line": null,
  "reviewUrl": null,
  "artifacts": [],
  "relatedTickets": [],
  "createdAt": "2025-06-09T00:41:15.663Z",
  "updatedAt": "2025-06-09T00:41:15.663Z",
  "timestamp": "2025-06-09T00:41:15.663Z",
  "history": [],
  "verification": []
}